{"header": {"index": 70630, "nonce": 95408, "previous_hash": "0000b4bbe11bd586ae898508b023012b83ab0b64427ce12fb23b84c8ee4daa44", "timestamp": 1547396825.7088068}, "transactions": [{"amount": 7.155772750948476, "index": 153, "receiver": "alice", "sender": "bob"}, {"amount": 14.922891775152522, "index": 154, "receiver": "alice", "sender": "julien"}, {"amount": 13.97033345848724, "index": 155, "receiver": "bob", "sender": "alice"}, {"amount": 10.563053104717858, "index": 156, "receiver": "julien", "sender": "bob"}, {"amount": 12.74297243993519, "index": 157, "receiver": "jonathan", "sender": "julien"}, {"amount": 10.17486858174286, "index": 158, "receiver": "nicoleta", "sender": "jonathan"}, {"amount": 5.08743429087143, "index": 159, "receiver": "bob", "sender": "jonathan"}, {"amount": 6.98516672924362, "index": 160, "receiver": "bob", "sender": "alice"}, {"amount": 0.7923175400490444, "index": 161, "receiver": "bob", "sender": "fabian"}, {"amount": 0.3961587700245222, "index": 162, "receiver": "jonathan", "sender": "fabian"}, {"amount": 6.371486219967595, "index": 163, "receiver": "alice", "sender": "julien"}, {"amount": 11.713985832440976, "index": 164, "receiver": "alice", "sender": "bob"}, {"amount": 5.482068667509387, "index": 165, "receiver": "alice", "sender": "nicoleta"}, {"amount": 2.741796530447976, "index": 166, "receiver": "fabian", "sender": "jonathan"}, {"amount": 5.856992916220488, "index": 167, "receiver": "alice", "sender": "bob"}, {"amount": 1.5689776502362491, "index": 168, "receiver": "alice", "sender": "fabian"}, {"amount": 2.7410343337546936, "index": 169, "receiver": "alice", "sender": "nicoleta"}, {"amount": 1.370898265223988, "index": 170, "receiver": "bob", "sender": "jonathan"}]}